COPYING
ChangeLog
MANIFEST.in
README
setup.py
./__init__.py
./__pkginfo__.py
./hmi/__init__.py
./hmi/console.py
./lib/__init__.py
./lib/archives.py
./lib/create.py
./lib/migrate.py
./lib/restore.py
./lib/resume.py
./lib/save.py
./lib/show.py
./lib/start.py
./lib/stop.py
./lib/suspend.py
./lib/test/__init__.py
./lib/test/clear.py
./lib/test/init.py
./lib/test/unittest_create.py
./lib/test/unittest_save_restore.py
./lib/test/unittest_show.py
./lib/test/unittest_start.py
./lib/test/unittest_stop.py
./lib/test/unittest_suspend_resume.py
bin/logilabvm
conf/settings.ini
doc/dummy.sh
doc/logilabvm.1
doc/logilabvm.1.gz
hooks/example.py
hooks/example.sh
hooks/openvz_migrate.sh
lib/test/101.xml
lib/test/102.xml
lib/test/kvm01.xml
lib/test/kvm02.xml
logilabvm.egg-info/PKG-INFO
logilabvm.egg-info/SOURCES.txt
logilabvm.egg-info/dependency_links.txt
logilabvm.egg-info/top_level.txt
scripts/openvz_dev.sh
scripts/openvz_failure.sh
scripts/openvz_net.sh
scripts/openvz_other.sh
scripts/openvz_post.sh
scripts/openvz_pre.sh
scripts/openvz_sys.sh
scripts/qemu_dev.sh
scripts/qemu_failure.sh
scripts/qemu_net.sh
scripts/qemu_other.sh
scripts/qemu_post.sh
scripts/qemu_pre.sh
scripts/qemu_sys.sh
scripts/echo/openvz_dev.sh
scripts/echo/openvz_failure.sh
scripts/echo/openvz_net.sh
scripts/echo/openvz_other.sh
scripts/echo/openvz_post.sh
scripts/echo/openvz_pre.sh
scripts/echo/openvz_sys.sh
scripts/echo/qemu_dev.sh
scripts/echo/qemu_failure.sh
scripts/echo/qemu_net.sh
scripts/echo/qemu_other.sh
scripts/echo/qemu_post.sh
scripts/echo/qemu_pre.sh
scripts/echo/qemu_sys.sh