Metadata-Version: 1.0
Name: logilabvm
Version: 0.1
Summary: useful miscellaneous modules used by Logilab projects
Home-page: http://www.logilab.org/project/logilabvm
Author: Logilab
Author-email: devel@logilab.fr
License: GPL
Platform: UNKNOWN
